__init__.py
test.py
hoime_sdk/__init__.py
hoime_sdk/api/__init__.py
hoime_sdk/api/user.py
hoime_sdk/tools/__init__.py
hoime_sdk-1.0.0.3.dist-info/METADATA
hoime_sdk-1.0.0.3.dist-info/WHEEL
hoime_sdk-1.0.0.3.dist-info/top_level.txt
hoime_sdk-1.0.0.3.dist-info/RECORD
