Metadata-Version: 2.1
Name: hoime-sdk
Version: 1.0.0.3
Summary: Hoime official SDK toolkit
Author-email: French <french@hoime.cn>
Project-URL: Homepage, https://github.com/hoime-wock/hoime_sdk
Project-URL: Bug Tracker, https://github.com/hoime-wock/hoime_sdk/issues
Classifier: Programming Language :: Python :: 3
Classifier: License :: OSI Approved :: Mozilla Public License 2.0 (MPL 2.0)
Classifier: Operating System :: OS Independent
Requires-Python: >=3
